text2hologram/__main__.py
text2hologram/color_recon.py
text2hologram/config.json
text2hologram/device_setup.py
text2hologram/image_generation.py
text2hologram/image_processing_utils.py
text2hologram/model.py
text2hologram/post_processing.py
text2hologram/settings.py
text2hologram/super_resolution.py
text2hologram/utils.py
text2hologram-0.1.5.3.dist-info/METADATA
text2hologram-0.1.5.3.dist-info/WHEEL
text2hologram-0.1.5.3.dist-info/entry_points.txt
text2hologram-0.1.5.3.dist-info/top_level.txt
text2hologram-0.1.5.3.dist-info/RECORD
