Metadata-Version: 2.1
Name: text2hologram
Version: 0.1.5.3
Summary: Generate holograms from text
Author-email: Pengze Li <linsonng@163.com>
Project-URL: Homepage, https://github.com/Linsonng/text2hologram
Keywords: text,hologram
Classifier: License :: OSI Approved :: MIT License
Classifier: Programming Language :: Python
Classifier: Programming Language :: Python :: 3
Requires-Python: >=3.9
Requires-Dist: odak ==0.2.3
Requires-Dist: timm ==0.9.2
Requires-Dist: transformers ==4.30.2
Requires-Dist: diffusers ==0.17.1
Requires-Dist: accelerate ==0.20.3
Requires-Dist: torch >=2.0.1
Requires-Dist: openvino ==2023.0.1
